{
  "generator-jhipster": {
    "applicationType": "monolith",
    "gitHubOrganization": "elvisimo",
    "baseName": "jhipsterSampleApplication",
    "packageName": "ru.silend.blog.sas",
    "serverPort": 80,
    "serviceDiscoveryType": "false",
    "authenticationType": "session",
    "uaaBaseName": "../uaa",
    "hibernateCache": "ehcache",
    "clusteredHttpSession": false,
    "websocket": false,
    "databaseType": "sql",
    "devDatabaseType": "h2Disk",
    "prodDatabaseType": "postgresql",
    "searchEngine": false,
    "enableSwaggerCodegen": false,
    "messageBroker": false,
    "buildTool": "maven",
    "enableSocialSignIn": true,
    "useSass": false,
    "clientPackageManager": "yarn",
    "testFrameworks": [
      "cucumber"
    ],
    "enableTranslation": true,
    "nativeLanguage": "en",
    "languages": [
      "ru"
    ],
    "clientFramework": "angularX",
    "jhipsterVersion": "4.9.0",
    "packageFolder": "ru/silend/blog/sas",
    "rememberMeKey": "66fc7e1a04774a0d37848995e3e9c93c77891297",
    "jhiPrefix": "jhi"
  }
}